{
  "dist/index.cjs.js": {
    "bundled": 76647,
    "minified": 48901,
    "gzipped": 10563
  },
  "dist/index.esm.js": {
    "bundled": 74018,
    "minified": 46384,
    "gzipped": 10389,
    "treeshaked": {
      "rollup": {
        "code": 35717,
        "import_statements": 807
      },
      "webpack": {
        "code": 39568
      }
    }
  },
  "index.cjs.js": {
    "bundled": 83051,
    "minified": 51288,
    "gzipped": 11114
  },
  "index.esm.js": {
    "bundled": 80243,
    "minified": 48592,
    "gzipped": 10941,
    "treeshaked": {
      "rollup": {
        "code": 37727,
        "import_statements": 807
      },
      "webpack": {
        "code": 41885
      }
    }
  }
}
