{
  "dist/index.cjs.js": {
    "bundled": 76647,
    "minified": 48901,
    "gzipped": 10563
  },
  "dist/index.esm.js": {
    "bundled": 74018,
    "minified": 46384,
    "gzipped": 10389,
    "treeshaked": {
      "rollup": {
        "code": 35717,
        "import_statements": 807
      },
      "webpack": {
        "code": 39568
      }
    }
  },
  "index.cjs.js": {
    "bundled": 82507,
    "minified": 50815,
    "gzipped": 10860
  },
  "index.esm.js": {
    "bundled": 79680,
    "minified": 48101,
    "gzipped": 10694,
    "treeshaked": {
      "rollup": {
        "code": 37055,
        "import_statements": 792
      },
      "webpack": {
        "code": 41281
      }
    }
  }
}
