{
  "dist/index.cjs.js": {
    "bundled": 25198,
    "minified": 18085,
    "gzipped": 4559
  },
  "dist/index.esm.js": {
    "bundled": 24305,
    "minified": 17261,
    "gzipped": 4439,
    "treeshaked": {
      "rollup": {
        "code": 13398,
        "import_statements": 383
      },
      "webpack": {
        "code": 15270
      }
    }
  },
  "index.cjs.js": {
    "bundled": 26591,
    "minified": 19052,
    "gzipped": 4638
  },
  "index.esm.js": {
    "bundled": 24631,
    "minified": 17349,
    "gzipped": 4485,
    "treeshaked": {
      "rollup": {
        "code": 13655,
        "import_statements": 383
      },
      "webpack": {
        "code": 15526
      }
    }
  }
}
