{
  "dist/index.cjs.js": {
    "bundled": 25198,
    "minified": 18085,
    "gzipped": 4559
  },
  "dist/index.esm.js": {
    "bundled": 24305,
    "minified": 17261,
    "gzipped": 4439,
    "treeshaked": {
      "rollup": {
        "code": 13398,
        "import_statements": 383
      },
      "webpack": {
        "code": 15270
      }
    }
  },
  "index.cjs.js": {
    "bundled": 25614,
    "minified": 18301,
    "gzipped": 4573
  },
  "index.esm.js": {
    "bundled": 24723,
    "minified": 17479,
    "gzipped": 4457,
    "treeshaked": {
      "rollup": {
        "code": 13569,
        "import_statements": 383
      },
      "webpack": {
        "code": 15440
      }
    }
  }
}
